odoo/addons/disable_odoo_online/README.rst
odoo/addons/disable_odoo_online/__init__.py
odoo/addons/disable_odoo_online/__manifest__.py
odoo/addons/disable_odoo_online/i18n/de.po
odoo/addons/disable_odoo_online/i18n/disable_odoo_online.pot
odoo/addons/disable_odoo_online/i18n/es.po
odoo/addons/disable_odoo_online/i18n/fr.po
odoo/addons/disable_odoo_online/i18n/hr.po
odoo/addons/disable_odoo_online/i18n/hr_HR.po
odoo/addons/disable_odoo_online/i18n/it.po
odoo/addons/disable_odoo_online/i18n/nl_NL.po
odoo/addons/disable_odoo_online/i18n/pt_BR.po
odoo/addons/disable_odoo_online/i18n/sl.po
odoo/addons/disable_odoo_online/models/__init__.py
odoo/addons/disable_odoo_online/models/publisher_warranty_contract.py
odoo/addons/disable_odoo_online/readme/CONTRIBUTORS.md
odoo/addons/disable_odoo_online/readme/DESCRIPTION.md
odoo/addons/disable_odoo_online/static/description/icon.png
odoo/addons/disable_odoo_online/static/description/index.html
odoo/addons/disable_odoo_online/static/src/js/user_menu_items.esm.js
odoo/addons/disable_odoo_online/tests/__init__.py
odoo/addons/disable_odoo_online/tests/test_disable_odoo_online.py
odoo/addons/disable_odoo_online/views/ir_ui_menu.xml
odoo_addon_disable_odoo_online-19.0.1.0.0.2.dist-info/METADATA
odoo_addon_disable_odoo_online-19.0.1.0.0.2.dist-info/WHEEL
odoo_addon_disable_odoo_online-19.0.1.0.0.2.dist-info/top_level.txt
odoo_addon_disable_odoo_online-19.0.1.0.0.2.dist-info/RECORD
